tests/__init__.py
tests/test_cache.py
tests/test_config.py
tests/test_integration.py
tests/test_resource_matcher.py
tests/test_ssl_verify.py
tests/test_summary.py
tests/test_utils.py
zephy/PRIMARY_RESOURCE_TYPES.json
zephy/__init__.py
zephy/__main__.py
zephy/__version__.py
zephy/auth.py
zephy/azure_client.py
zephy/cache.py
zephy/config.py
zephy/constants.py
zephy/logger.py
zephy/report_generator.py
zephy/resource_matcher.py
zephy/tfe_client.py
zephy/utils.py
zephy-1.1.3.dist-info/licenses/LICENSE
zephy-1.1.3.dist-info/METADATA
zephy-1.1.3.dist-info/WHEEL
zephy-1.1.3.dist-info/entry_points.txt
zephy-1.1.3.dist-info/top_level.txt
zephy-1.1.3.dist-info/RECORD
